README.md
setup.py
wksort/__init__.py
wksort/bubblesort.py
wksort/heapsort.py
wksort/insertsort.py
wksort/mergesort.py
wksort/quicksort.py
wksort/radixsort.py
wksort/selectionsort.py
wksort/wksort.py
wksort.egg-info/PKG-INFO
wksort.egg-info/SOURCES.txt
wksort.egg-info/dependency_links.txt
wksort.egg-info/not-zip-safe
wksort.egg-info/top_level.txt