Metadata-Version: 1.0
Name: wksort
Version: 0.0.1
Summary: This is a lib of realizing sort methods
Home-page: https://github.com/naizut/wksort
Author: Wenkai Zhou
Author-email: naizut@163.com
License: MIT
Platform: UNKNOWN
